sqlalchemy_mixins/__init__.py
sqlalchemy_mixins/active_record.py
sqlalchemy_mixins/base_query.py
sqlalchemy_mixins/crud_mixin.py
sqlalchemy_mixins/date_mixin.py
sqlalchemy_mixins/eager_load.py
sqlalchemy_mixins/exception.py
sqlalchemy_mixins/image_mixin.py
sqlalchemy_mixins/inspection_mixin.py
sqlalchemy_mixins/repr_mixin.py
sqlalchemy_mixins/session_mixin.py
sqlalchemy_mixins/smart_query.py
sqlalchemy_mixins/user_mixin.py
sqlalchemy_mixins/util.py
sqlalchemy_mixins/extra/__init__.py
sqlalchemy_mixins/extra/helper.py
sqlalchemy_mixins/extra/phone_number.py
SqlalchemyMixin-0.0.39.dist-info/LICENSE
SqlalchemyMixin-0.0.39.dist-info/METADATA
SqlalchemyMixin-0.0.39.dist-info/WHEEL
SqlalchemyMixin-0.0.39.dist-info/top_level.txt
SqlalchemyMixin-0.0.39.dist-info/RECORD
