Metadata-Version: 2.1
Name: SqlalchemyMixin
Version: 0.0.39
Summary: Active Record, Django-like queries, nested eager load and beauty __repr__ for SQLAlchemy
Home-page: https://github.com/blueromans/SqlalchemyMixin.git
Author: Yaşar Özyurt
Author-email: blueromans@gmail.com
Project-URL: Bug Tracker, https://github.com/blueromans/SqlalchemyMixin/issues
Keywords: sqlalchemy,active record,activerecord,orm,django-like,django,eager load,eagerload,repr,__repr__,mysql,postgresql,pymysql,sqlite
Classifier: Programming Language :: Python :: 3
Classifier: License :: OSI Approved :: MIT License
Classifier: Operating System :: OS Independent
Requires-Python: >=3.6
License-File: LICENSE
Requires-Dist: SQLAlchemy (>=1.0)
Requires-Dist: six
Requires-Dist: python-slugify
Requires-Dist: phonenumbers
Requires-Dist: arrow
Requires-Dist: typing ; python_version < "3.5"
